{
  "name": "Single-Leg Hop Progression",
  "force": "push",
  "level": "beginner",
  "mechanic": "compound",
  "equipment": "other",
  "primaryMuscles": [
    "quadriceps"
  ],
  "secondaryMuscles": [
    "abductors",
    "adductors",
    "calves",
    "hamstrings"
  ],
  "instructions": [
    "Arrange a line of cones in front of you. Assume a relaxed standing position, balanced on one leg. Raise the knee of your opposite leg. This will be your starting position.",
    "Hop forward, jumping and landing with the same leg over the cone.",
    "Use a countermovement jump to hop from cone to cone.",
    "At the end, turn around and go back on the other leg."
  ],
  "category": "plyometrics",
  "images": [
    "Single-Leg_Hop_Progression/0.jpg",
    "Single-Leg_Hop_Progression/1.jpg"
  ],
  "id": "Single-Leg_Hop_Progression"
}